coralearn/__init__.py
coralearn/activations/__init__.py
coralearn/activations/linear_activation.py
coralearn/activations/relu.py
coralearn/activations/sigmoid.py
coralearn/activations/softmax.py
coralearn/losses/__init__.py
coralearn/losses/binary_cross_entropy.py
coralearn/losses/mse.py
coralearn/losses/sparse_categorical_cross_entropy.py
coralearn/models/__init__.py
coralearn/models/classical/__init__.py
coralearn/models/classical/basemodel.py
coralearn/models/classical/linear.py
coralearn/models/classical/polynomial.py
coralearn/models/classification/__init__.py
coralearn/models/classification/k_nearest_neighbor.py
coralearn/models/classification/logistic_regression.py
coralearn/neural_network/Dense.py
coralearn/neural_network/Sequential.py
coralearn/neural_network/__init__.py
coralearn/optimizers/AdaGrad.py
coralearn/optimizers/Adam.py
coralearn/optimizers/NAG.py
coralearn/optimizers/Optimizer.py
coralearn/optimizers/RMSprop.py
coralearn/optimizers/SGD.py
coralearn/optimizers/SGDMomentum.py
coralearn/optimizers/__init__.py
coralearn/scalers/__init__.py
coralearn/scalers/min_max_scaler.py
coralearn/scalers/robust_scaler.py
coralearn/scalers/standard_scaler.py
coralearn-0.2.1.dist-info/licenses/LICENSE
coralearn-0.2.1.dist-info/METADATA
coralearn-0.2.1.dist-info/WHEEL
coralearn-0.2.1.dist-info/top_level.txt
coralearn-0.2.1.dist-info/RECORD
