Metadata-Version: 2.4
Name: coralearn
Version: 0.2.1
Summary: An AI library written using only NumPy
Home-page: https://github.com/Coralap/CoraLearn
Author: Coralap
Classifier: Programming Language :: Python :: 3
Classifier: License :: OSI Approved :: MIT License
Classifier: Operating System :: OS Independent
Requires-Python: >=3.8
License-File: LICENSE
Dynamic: author
Dynamic: classifier
Dynamic: description
Dynamic: description-content-type
Dynamic: home-page
Dynamic: license-file
Dynamic: requires-python
Dynamic: summary
